exjson.py
exjson-1.0.2.dist-info/METADATA
exjson-1.0.2.dist-info/RECORD
exjson-1.0.2.dist-info/WHEEL
exjson-1.0.2.dist-info/top_level.txt
scripting/__init__.py
scripting/extensions/__init__.py
scripting/extensions/cryptography.py
scripting/extensions/datetime.py
scripting/extensions/io.py
scripting/extensions/sequences.py
scripting/extensions/tools.py
tests/tools/__init__.py
